JupyterGPT/__init__.py
JupyterGPT/_version.py
jupytergpt-0.1.0.data/data/share/jupyter/labextensions/JupyterGPT/build_log.json
jupytergpt-0.1.0.data/data/share/jupyter/labextensions/JupyterGPT/package.json
jupytergpt-0.1.0.data/data/share/jupyter/labextensions/JupyterGPT/static/lib_index_js.c10461cb42ec2865414b.js
jupytergpt-0.1.0.data/data/share/jupyter/labextensions/JupyterGPT/static/lib_index_js.c10461cb42ec2865414b.js.map
jupytergpt-0.1.0.data/data/share/jupyter/labextensions/JupyterGPT/static/remoteEntry.9ef44a1856de565ba63f.js
jupytergpt-0.1.0.data/data/share/jupyter/labextensions/JupyterGPT/static/remoteEntry.9ef44a1856de565ba63f.js.map
jupytergpt-0.1.0.data/data/share/jupyter/labextensions/JupyterGPT/static/style.js
jupytergpt-0.1.0.data/data/share/jupyter/labextensions/JupyterGPT/static/style_index_js.dd319ac20d1a7c13db95.js
jupytergpt-0.1.0.data/data/share/jupyter/labextensions/JupyterGPT/static/style_index_js.dd319ac20d1a7c13db95.js.map
jupytergpt-0.1.0.data/data/share/jupyter/labextensions/JupyterGPT/static/vendors-node_modules_css-loader_dist_runtime_api_js-node_modules_css-loader_dist_runtime_cssW-72eba1.27ac51121c003a95230d.js
jupytergpt-0.1.0.data/data/share/jupyter/labextensions/JupyterGPT/static/vendors-node_modules_css-loader_dist_runtime_api_js-node_modules_css-loader_dist_runtime_cssW-72eba1.27ac51121c003a95230d.js.map
jupytergpt-0.1.0.data/data/share/jupyter/labextensions/JupyterGPT/install.json
jupytergpt-0.1.0.dist-info/METADATA
jupytergpt-0.1.0.dist-info/WHEEL
jupytergpt-0.1.0.dist-info/licenses/LICENSE
jupytergpt-0.1.0.dist-info/RECORD
